dbmanager/__init__.py
dbmanager/main.py
dbmngrx-0.1.2.dist-info/METADATA
dbmngrx-0.1.2.dist-info/WHEEL
dbmngrx-0.1.2.dist-info/top_level.txt
dbmngrx-0.1.2.dist-info/RECORD
