Metadata-Version: 2.4
Name: dbmngrx
Version: 0.1.2
Summary: Simple DB manager library
Author-email: Otabek <burhonovotabek5@gmail.com>
Project-URL: Homepage, https://example.com/dbmanager
Requires-Python: >=3.7
